sqlitewebviewer/__init__.py
sqlitewebviewer/app.py
sqlitewebviewer-1.0.1.dist-info/METADATA
sqlitewebviewer-1.0.1.dist-info/WHEEL
sqlitewebviewer-1.0.1.dist-info/entry_points.txt
sqlitewebviewer-1.0.1.dist-info/top_level.txt
sqlitewebviewer-1.0.1.dist-info/RECORD
