Metadata-Version: 2.4
Name: sqlitewebviewer
Version: 1.0.1
Summary: A web-based SQLite browser and query tool
Home-page: https://github.com/mandeepcheema/sqlitewebviewer
Author: Mandeep Cheema
Author-email: 
License: MIT
Project-URL: Source, https://github.com/mandeepcheema/sqlitewebviewer
Project-URL: Issues, https://github.com/mandeepcheema/sqlitewebviewer/issues
Classifier: Programming Language :: Python :: 3
Classifier: License :: OSI Approved :: MIT License
Classifier: Framework :: Flask
Classifier: Environment :: Web Environment
Classifier: Intended Audience :: Developers
Classifier: Topic :: Database
Classifier: Topic :: Internet :: WWW/HTTP :: Dynamic Content
Classifier: Operating System :: OS Independent
Requires-Python: >=3.8
Requires-Dist: Flask>=2.2
Dynamic: author
Dynamic: classifier
Dynamic: description
Dynamic: description-content-type
Dynamic: home-page
Dynamic: license
Dynamic: project-url
Dynamic: requires-dist
Dynamic: requires-python
Dynamic: summary
